pyextendable/__init__.py
pyextendable/config.py
pyextendable/ecosystem.py
pyextendable/errors.py
pyextendable/toolkit.py
pyextendable/utilities.py
pyextendable/events/__init__.py
pyextendable/events/dispatch.py
pyextendable/events/observe.py
pyextendable/events/subscribe.py
pyextendable/expansions/__init__.py
pyextendable/expansions/expand.py
pyextendable/expansions/extensions/__init__.py
pyextendable/expansions/extensions/framework.py
pyextendable/expansions/extensions/metadata.py
pyextendable/expansions/plugins/__init__.py
pyextendable/expansions/plugins/loader.py
pyextendable/expansions/plugins/manager.py
pyextendable/hooks/__init__.py
pyextendable/hooks/core_hooks.py
pyextendable/hooks/hooked.py
pyextendable/hooks/register.py
pyextendable-0.1.0.dist-info/LICENSE.md
pyextendable-0.1.0.dist-info/METADATA
pyextendable-0.1.0.dist-info/WHEEL
pyextendable-0.1.0.dist-info/top_level.txt
pyextendable-0.1.0.dist-info/RECORD
