Metadata-Version: 2.2
Name: pyextendable
Version: 0.1.0
Summary: A PyForge Ecosytem Project for adaptability, modular and extendable.
Author-email: Aidan Hogg <aidan.hogg@dirtywork.solutions>
License: # CC0 1.0 Universal
Project-URL: Homepage, https://open.dirtywork.solutions/pyextend
Project-URL: Documentation, https://open.dirtywork.solutions/pyextend/docs
Project-URL: Source, https://github.com/DirtyWork-Solutions/PyExtend
Project-URL: Issues, https://github.com/DirtyWork-Solutions/PyExtend/tree/main/.github/ISSUE_TEMPLATE
License-File: LICENSE.md
Requires-Dist: pyutils
